[{
	"id": "33024",
	"vodId": null,
	"typeId": null,
	"vodName": "伏魔录之灵山之谜",
	"vodSub": null,
	"vodTag": null,
	"vodClass": null,
	"vodPic": "https://z3.ax1x.com/2021/08/26/hmHOde.png",
	"vodActor": null,
	"vodDirector": null,
	"vodWriter": null,
	"vodBlurb": null,
	"vodRemarks": "BD1080P国语中字",
	"vodArea": null,
	"vodLang": null,
	"vodYear": null,
	"vodVersion": null,
	"vodState": null,
	"vodAuthor": null,
	"vodDuration": null,
	"vodTime": null,
	"vodTimeAdd": null,
	"vodDoubanId": null,
	"vodDoubanScore": null,
	"vodContent": null,
	"vodPlayUrl": null,
	"typeName": null,
	"classify": null
}, {
	"id": "33015",
	"vodId": null,
	"typeId": null,
	"vodName": "伏魔录",
	"vodSub": null,
	"vodTag": null,
	"vodClass": null,
	"vodPic": "https://z3.ax1x.com/2021/08/26/hmHOde.png",
	"vodActor": null,
	"vodDirector": null,
	"vodWriter": null,
	"vodBlurb": null,
	"vodRemarks": "BD1080P国语中字",
	"vodArea": null,
	"vodLang": null,
	"vodYear": null,
	"vodVersion": null,
	"vodState": null,
	"vodAuthor": null,
	"vodDuration": null,
	"vodTime": null,
	"vodTimeAdd": null,
	"vodDoubanId": null,
	"vodDoubanScore": null,
	"vodContent": null,
	"vodPlayUrl": null,
	"typeName": null,
	"classify": null
}, {
	"id": "33136",
	"vodId": null,
	"typeId": null,
	"vodName": "特殊保镖4明日战神蓝理",
	"vodSub": null,
	"vodTag": null,
	"vodClass": null,
	"vodPic": "https://z3.ax1x.com/2021/08/26/hmHOde.png",
	"vodActor": null,
	"vodDirector": null,
	"vodWriter": null,
	"vodBlurb": null,
	"vodRemarks": "BD1080P国语中字",
	"vodArea": null,
	"vodLang": null,
	"vodYear": null,
	"vodVersion": null,
	"vodState": null,
	"vodAuthor": null,
	"vodDuration": null,
	"vodTime": null,
	"vodTimeAdd": null,
	"vodDoubanId": null,
	"vodDoubanScore": null,
	"vodContent": null,
	"vodPlayUrl": null,
	"typeName": null,
	"classify": null
}, {
	"id": "33133",
	"vodId": null,
	"typeId": null,
	"vodName": "特殊保镖2",
	"vodSub": null,
	"vodTag": null,
	"vodClass": null,
	"vodPic": "https://z3.ax1x.com/2021/08/26/hmHOde.png",
	"vodActor": null,
	"vodDirector": null,
	"vodWriter": null,
	"vodBlurb": null,
	"vodRemarks": "BD1080P国语中字",
	"vodArea": null,
	"vodLang": null,
	"vodYear": null,
	"vodVersion": null,
	"vodState": null,
	"vodAuthor": null,
	"vodDuration": null,
	"vodTime": null,
	"vodTimeAdd": null,
	"vodDoubanId": null,
	"vodDoubanScore": null,
	"vodContent": null,
	"vodPlayUrl": null,
	"typeName": null,
	"classify": null
}, {
	"id": "33042",
	"vodId": null,
	"typeId": null,
	"vodName": "甜心女孩",
	"vodSub": null,
	"vodTag": null,
	"vodClass": null,
	"vodPic": "https://z3.ax1x.com/2021/08/26/hmHOde.png",
	"vodActor": null,
	"vodDirector": null,
	"vodWriter": null,
	"vodBlurb": null,
	"vodRemarks": "BD1080P英语中字",
	"vodArea": null,
	"vodLang": null,
	"vodYear": null,
	"vodVersion": null,
	"vodState": null,
	"vodAuthor": null,
	"vodDuration": null,
	"vodTime": null,
	"vodTimeAdd": null,
	"vodDoubanId": null,
	"vodDoubanScore": null,
	"vodContent": null,
	"vodPlayUrl": null,
	"typeName": null,
	"classify": null
}, {
	"id": "33209",
	"vodId": null,
	"typeId": null,
	"vodName": "龙脉·八幡神域",
	"vodSub": null,
	"vodTag": null,
	"vodClass": null,
	"vodPic": "https://z3.ax1x.com/2021/08/26/hmHOde.png",
	"vodActor": null,
	"vodDirector": null,
	"vodWriter": null,
	"vodBlurb": null,
	"vodRemarks": "BD1080P国语中字",
	"vodArea": null,
	"vodLang": null,
	"vodYear": null,
	"vodVersion": null,
	"vodState": null,
	"vodAuthor": null,
	"vodDuration": null,
	"vodTime": null,
	"vodTimeAdd": null,
	"vodDoubanId": null,
	"vodDoubanScore": null,
	"vodContent": null,
	"vodPlayUrl": null,
	"typeName": null,
	"classify": null
}, {
	"id": "33164",
	"vodId": null,
	"typeId": null,
	"vodName": "太太请小心轻放电影版",
	"vodSub": null,
	"vodTag": null,
	"vodClass": null,
	"vodPic": "https://z3.ax1x.com/2021/08/26/hmHOde.png",
	"vodActor": null,
	"vodDirector": null,
	"vodWriter": null,
	"vodBlurb": null,
	"vodRemarks": "BD1080P日语中字",
	"vodArea": null,
	"vodLang": null,
	"vodYear": null,
	"vodVersion": null,
	"vodState": null,
	"vodAuthor": null,
	"vodDuration": null,
	"vodTime": null,
	"vodTimeAdd": null,
	"vodDoubanId": null,
	"vodDoubanScore": null,
	"vodContent": null,
	"vodPlayUrl": null,
	"typeName": null,
	"classify": null
}, {
	"id": "33124",
	"vodId": null,
	"typeId": null,
	"vodName": "蝙蝠侠",
	"vodSub": null,
	"vodTag": null,
	"vodClass": null,
	"vodPic": "https://z3.ax1x.com/2021/08/26/hmHOde.png",
	"vodActor": null,
	"vodDirector": null,
	"vodWriter": null,
	"vodBlurb": null,
	"vodRemarks": "BD1080P中文字幕",
	"vodArea": null,
	"vodLang": null,
	"vodYear": null,
	"vodVersion": null,
	"vodState": null,
	"vodAuthor": null,
	"vodDuration": null,
	"vodTime": null,
	"vodTimeAdd": null,
	"vodDoubanId": null,
	"vodDoubanScore": null,
	"vodContent": null,
	"vodPlayUrl": null,
	"typeName": null,
	"classify": null
}, {
	"id": "33301",
	"vodId": null,
	"typeId": null,
	"vodName": "猎魔人狼之噩梦",
	"vodSub": null,
	"vodTag": null,
	"vodClass": null,
	"vodPic": "https://z3.ax1x.com/2021/08/26/hmHOde.png",
	"vodActor": null,
	"vodDirector": null,
	"vodWriter": null,
	"vodBlurb": null,
	"vodRemarks": "BD1080P中文字幕",
	"vodArea": null,
	"vodLang": null,
	"vodYear": null,
	"vodVersion": null,
	"vodState": null,
	"vodAuthor": null,
	"vodDuration": null,
	"vodTime": null,
	"vodTimeAdd": null,
	"vodDoubanId": null,
	"vodDoubanScore": null,
	"vodContent": null,
	"vodPlayUrl": null,
	"typeName": null,
	"classify": null
}, {
	"id": "33276",
	"vodId": null,
	"typeId": null,
	"vodName": "西游记之再世妖王",
	"vodSub": null,
	"vodTag": null,
	"vodClass": null,
	"vodPic": "https://z3.ax1x.com/2021/08/26/hmHOde.png",
	"vodActor": null,
	"vodDirector": null,
	"vodWriter": null,
	"vodBlurb": null,
	"vodRemarks": "BD1080P国语中字",
	"vodArea": null,
	"vodLang": null,
	"vodYear": null,
	"vodVersion": null,
	"vodState": null,
	"vodAuthor": null,
	"vodDuration": null,
	"vodTime": null,
	"vodTimeAdd": null,
	"vodDoubanId": null,
	"vodDoubanScore": null,
	"vodContent": null,
	"vodPlayUrl": null,
	"typeName": null,
	"classify": null
}, {
	"id": "31871",
	"vodId": null,
	"typeId": null,
	"vodName": "天下第一镖局2长风厉",
	"vodSub": null,
	"vodTag": null,
	"vodClass": null,
	"vodPic": "https://z3.ax1x.com/2021/08/26/hmHOde.png",
	"vodActor": null,
	"vodDirector": null,
	"vodWriter": null,
	"vodBlurb": null,
	"vodRemarks": "HD",
	"vodArea": null,
	"vodLang": null,
	"vodYear": null,
	"vodVersion": null,
	"vodState": null,
	"vodAuthor": null,
	"vodDuration": null,
	"vodTime": null,
	"vodTimeAdd": null,
	"vodDoubanId": null,
	"vodDoubanScore": null,
	"vodContent": null,
	"vodPlayUrl": null,
	"typeName": null,
	"classify": null
}, {
	"id": "33603",
	"vodId": null,
	"typeId": null,
	"vodName": "重生之鬼",
	"vodSub": null,
	"vodTag": null,
	"vodClass": null,
	"vodPic": "https://z3.ax1x.com/2021/08/26/hmHOde.png",
	"vodActor": null,
	"vodDirector": null,
	"vodWriter": null,
	"vodBlurb": null,
	"vodRemarks": "HD",
	"vodArea": null,
	"vodLang": null,
	"vodYear": null,
	"vodVersion": null,
	"vodState": null,
	"vodAuthor": null,
	"vodDuration": null,
	"vodTime": null,
	"vodTimeAdd": null,
	"vodDoubanId": null,
	"vodDoubanScore": null,
	"vodContent": null,
	"vodPlayUrl": null,
	"typeName": null,
	"classify": null
}, {
	"id": "33935",
	"vodId": null,
	"typeId": null,
	"vodName": "死里逃生2021",
	"vodSub": null,
	"vodTag": null,
	"vodClass": null,
	"vodPic": "https://z3.ax1x.com/2021/08/26/hmHOde.png",
	"vodActor": null,
	"vodDirector": null,
	"vodWriter": null,
	"vodBlurb": null,
	"vodRemarks": "HD",
	"vodArea": null,
	"vodLang": null,
	"vodYear": null,
	"vodVersion": null,
	"vodState": null,
	"vodAuthor": null,
	"vodDuration": null,
	"vodTime": null,
	"vodTimeAdd": null,
	"vodDoubanId": null,
	"vodDoubanScore": null,
	"vodContent": null,
	"vodPlayUrl": null,
	"typeName": null,
	"classify": null
}, {
	"id": "33963",
	"vodId": null,
	"typeId": null,
	"vodName": "特种部队蛇眼起源",
	"vodSub": null,
	"vodTag": null,
	"vodClass": null,
	"vodPic": "https://z3.ax1x.com/2021/08/26/hmHOde.png",
	"vodActor": null,
	"vodDirector": null,
	"vodWriter": null,
	"vodBlurb": null,
	"vodRemarks": "HD",
	"vodArea": null,
	"vodLang": null,
	"vodYear": null,
	"vodVersion": null,
	"vodState": null,
	"vodAuthor": null,
	"vodDuration": null,
	"vodTime": null,
	"vodTimeAdd": null,
	"vodDoubanId": null,
	"vodDoubanScore": null,
	"vodContent": null,
	"vodPlayUrl": null,
	"typeName": null,
	"classify": null
}, {
	"id": "33540",
	"vodId": null,
	"typeId": null,
	"vodName": "劫持游侠",
	"vodSub": null,
	"vodTag": null,
	"vodClass": null,
	"vodPic": "https://z3.ax1x.com/2021/08/26/hmHOde.png",
	"vodActor": null,
	"vodDirector": null,
	"vodWriter": null,
	"vodBlurb": null,
	"vodRemarks": "HD",
	"vodArea": null,
	"vodLang": null,
	"vodYear": null,
	"vodVersion": null,
	"vodState": null,
	"vodAuthor": null,
	"vodDuration": null,
	"vodTime": null,
	"vodTimeAdd": null,
	"vodDoubanId": null,
	"vodDoubanScore": null,
	"vodContent": null,
	"vodPlayUrl": null,
	"typeName": null,
	"classify": null
}, {
	"id": "34023",
	"vodId": null,
	"typeId": null,
	"vodName": "狼人杀",
	"vodSub": null,
	"vodTag": null,
	"vodClass": null,
	"vodPic": "https://z3.ax1x.com/2021/08/26/hmHOde.png",
	"vodActor": null,
	"vodDirector": null,
	"vodWriter": null,
	"vodBlurb": null,
	"vodRemarks": "1080P",
	"vodArea": null,
	"vodLang": null,
	"vodYear": null,
	"vodVersion": null,
	"vodState": null,
	"vodAuthor": null,
	"vodDuration": null,
	"vodTime": null,
	"vodTimeAdd": null,
	"vodDoubanId": null,
	"vodDoubanScore": null,
	"vodContent": null,
	"vodPlayUrl": null,
	"typeName": null,
	"classify": null
}, {
	"id": "33990",
	"vodId": null,
	"typeId": null,
	"vodName": "济公之降龙降世",
	"vodSub": null,
	"vodTag": null,
	"vodClass": null,
	"vodPic": "https://z3.ax1x.com/2021/08/26/hmHOde.png",
	"vodActor": null,
	"vodDirector": null,
	"vodWriter": null,
	"vodBlurb": null,
	"vodRemarks": "1080P",
	"vodArea": null,
	"vodLang": null,
	"vodYear": null,
	"vodVersion": null,
	"vodState": null,
	"vodAuthor": null,
	"vodDuration": null,
	"vodTime": null,
	"vodTimeAdd": null,
	"vodDoubanId": null,
	"vodDoubanScore": null,
	"vodContent": null,
	"vodPlayUrl": null,
	"typeName": null,
	"classify": null
}, {
	"id": "33701",
	"vodId": null,
	"typeId": null,
	"vodName": "俑之城",
	"vodSub": null,
	"vodTag": null,
	"vodClass": null,
	"vodPic": "https://z3.ax1x.com/2021/08/26/hmHOde.png",
	"vodActor": null,
	"vodDirector": null,
	"vodWriter": null,
	"vodBlurb": null,
	"vodRemarks": "BD1080P国语中字",
	"vodArea": null,
	"vodLang": null,
	"vodYear": null,
	"vodVersion": null,
	"vodState": null,
	"vodAuthor": null,
	"vodDuration": null,
	"vodTime": null,
	"vodTimeAdd": null,
	"vodDoubanId": null,
	"vodDoubanScore": null,
	"vodContent": null,
	"vodPlayUrl": null,
	"typeName": null,
	"classify": null
}, {
	"id": "33746",
	"vodId": null,
	"typeId": null,
	"vodName": "厄运假期",
	"vodSub": null,
	"vodTag": null,
	"vodClass": null,
	"vodPic": "https://z3.ax1x.com/2021/08/26/hmHOde.png",
	"vodActor": null,
	"vodDirector": null,
	"vodWriter": null,
	"vodBlurb": null,
	"vodRemarks": "BD1080P中文字幕",
	"vodArea": null,
	"vodLang": null,
	"vodYear": null,
	"vodVersion": null,
	"vodState": null,
	"vodAuthor": null,
	"vodDuration": null,
	"vodTime": null,
	"vodTimeAdd": null,
	"vodDoubanId": null,
	"vodDoubanScore": null,
	"vodContent": null,
	"vodPlayUrl": null,
	"typeName": null,
	"classify": null
}, {
	"id": "33896",
	"vodId": null,
	"typeId": null,
	"vodName": "极速复仇2021",
	"vodSub": null,
	"vodTag": null,
	"vodClass": null,
	"vodPic": "https://z3.ax1x.com/2021/08/26/hmHOde.png",
	"vodActor": null,
	"vodDirector": null,
	"vodWriter": null,
	"vodBlurb": null,
	"vodRemarks": "HD",
	"vodArea": null,
	"vodLang": null,
	"vodYear": null,
	"vodVersion": null,
	"vodState": null,
	"vodAuthor": null,
	"vodDuration": null,
	"vodTime": null,
	"vodTimeAdd": null,
	"vodDoubanId": null,
	"vodDoubanScore": null,
	"vodContent": null,
	"vodPlayUrl": null,
	"typeName": null,
	"classify": null
}, {
	"id": "33987",
	"vodId": null,
	"typeId": null,
	"vodName": "鲨口逃生",
	"vodSub": null,
	"vodTag": null,
	"vodClass": null,
	"vodPic": "https://z3.ax1x.com/2021/08/26/hmHOde.png",
	"vodActor": null,
	"vodDirector": null,
	"vodWriter": null,
	"vodBlurb": null,
	"vodRemarks": "BD1080P国语中字",
	"vodArea": null,
	"vodLang": null,
	"vodYear": null,
	"vodVersion": null,
	"vodState": null,
	"vodAuthor": null,
	"vodDuration": null,
	"vodTime": null,
	"vodTimeAdd": null,
	"vodDoubanId": null,
	"vodDoubanScore": null,
	"vodContent": null,
	"vodPlayUrl": null,
	"typeName": null,
	"classify": null
}]
